ampdlib/__init__.py
ampdlib/ampdlib.py
ampdlib/tests/test.py
ampdlib-1.1.6.dist-info/LICENSE
ampdlib-1.1.6.dist-info/METADATA
ampdlib-1.1.6.dist-info/WHEEL
ampdlib-1.1.6.dist-info/top_level.txt
ampdlib-1.1.6.dist-info/RECORD
