Metadata-Version: 2.1
Name: ampdLib
Version: 1.1.6
Summary: Implementation of AMPD algorithm for peak detection in quasi-periodic signals
Project-URL: homepage, https://codeberg.org/LucaCerina/ampdLib
Project-URL: Bug Tracker, https://codeberg.org/LucaCerina/ampdLib/issues
Keywords: peak detection,signal processing,quasi-periodic signals
Classifier: Programming Language :: Python :: 3
Classifier: License :: OSI Approved :: Apache Software License
Classifier: Operating System :: OS Independent
Classifier: Development Status :: 5 - Production/Stable
Classifier: Topic :: Scientific/Engineering
Requires-Python: >=3.6
License-File: LICENSE
Requires-Dist: numpy
Provides-Extra: tests
Requires-Dist: scipy ; extra == 'tests'
